{
  "collectionName": "components_list_categories",
  "info": {
    "displayName": "Category",
    "description": ""
  },
  "options": {},
  "attributes": {
    "categories": {
      "type": "relation",
      "relation": "oneToMany",
      "target": "api::category.category",
      "pluginOptions": {
        "translate": {
          "translate": "translate"
        }
      }
    },
    "title": {
      "type": "string",
      "default": "Main Features",
      "pluginOptions": {
        "translate": {
          "translate": "translate"
        }
      }
    }
  }
}
